Metadata-Version: 2.1
Name: SnakesInSpace
Version: 0.0.23
Summary: A Python library for the SpaceTraders game
Author-email: Samuel Woodward <sam@woodward.fyi>
Project-URL: Homepage, https://github.com/PyWoody/SnakesInSpace
Keywords: SpaceTraders
Classifier: Programming Language :: Python :: 3
Classifier: License :: OSI Approved :: MIT License
Classifier: Operating System :: OS Independent
Requires-Python: >=3.9
License-File: LICENSE
Requires-Dist: httpx
Requires-Dist: python-dateutil >=2.9.0
